LICENSE
MANIFEST.in
NOTICE.md
README.md
setup.py
behave_asl.egg-info/PKG-INFO
behave_asl.egg-info/SOURCES.txt
behave_asl.egg-info/dependency_links.txt
behave_asl.egg-info/entry_points.txt
behave_asl.egg-info/requires.txt
behave_asl.egg-info/top_level.txt
behaveasl/__init__.py
behaveasl/assertions.py
behaveasl/cli.py
behaveasl/expr_eval.py
behaveasl/intrinsics.py
behaveasl/jsonata_eval.py
behaveasl/jsonpath.py
behaveasl/parser.py
behaveasl/wrapper.py
behaveasl/models/__init__.py
behaveasl/models/abstract_phase.py
behaveasl/models/abstract_state.py
behaveasl/models/catch.py
behaveasl/models/choice.py
behaveasl/models/exceptions.py
behaveasl/models/execution.py
behaveasl/models/query_language.py
behaveasl/models/retry.py
behaveasl/models/state_machine.py
behaveasl/models/state_models.py
behaveasl/models/state_phases.py
behaveasl/models/step_result.py
behaveasl/models/task_mock.py
behaveasl/steps/__init__.py
behaveasl/steps/given_steps.py
behaveasl/steps/then_steps.py
behaveasl/steps/when_steps.py