Metadata-Version: 2.1
Name: behave-asl
Version: 1.2.0
Summary: Cucumber-style unit testing of Step Functions
Home-page: https://github.com/vanguard-oss/behave-asl
Author: Vanguard
Author-email: opensource@vanguard.com
License: Apache License 2.0
Classifier: Development Status :: 5 - Production/Stable
Classifier: Intended Audience :: Developers
Classifier: Natural Language :: English
Classifier: License :: OSI Approved :: Apache Software License
Classifier: Programming Language :: Python :: 3
Classifier: Programming Language :: Python :: 3.9
Classifier: Programming Language :: Python :: 3.10
Classifier: Programming Language :: Python :: 3.11
License-File: LICENSE
License-File: NOTICE.md
Requires-Dist: behave>=1.0.25
Requires-Dist: diff_match_patch==20200713
Requires-Dist: jsonpath_ng<2.0.0
Requires-Dist: PyYAML>=5.4.1
Requires-Dist: jsonata-python
